rodents/__init__.py
rodents/jiggler.py
rodents-0.0.9.dist-info/LICENSE
rodents-0.0.9.dist-info/METADATA
rodents-0.0.9.dist-info/WHEEL
rodents-0.0.9.dist-info/entry_points.txt
rodents-0.0.9.dist-info/top_level.txt
rodents-0.0.9.dist-info/RECORD
